ncbi_datasets_util/__init__.py
ncbi_datasets_util/_modidx.py
ncbi_datasets_util/core.py
ncbi_datasets_util/download_and_qc.py
ncbi_datasets_util/downloader.py
ncbi_datasets_util/downloader_and_summarizer.py
ncbi_datasets_util/hello_world.py
ncbi_datasets_util/nucleotide_downloader.py
ncbi_datasets_util/nucleotide_downloader_and_summarizer.py
ncbi_datasets_util/nucleotide_summarizer.py
ncbi_datasets_util/some_string.py
ncbi_datasets_util/summarizer.py
ncbi_datasets_util/config/config.default.env
ncbi_datasets_util/config/config.default.yaml
ncbi_datasets_util-0.3.0.dist-info/LICENSE
ncbi_datasets_util-0.3.0.dist-info/METADATA
ncbi_datasets_util-0.3.0.dist-info/WHEEL
ncbi_datasets_util-0.3.0.dist-info/entry_points.txt
ncbi_datasets_util-0.3.0.dist-info/top_level.txt
ncbi_datasets_util-0.3.0.dist-info/RECORD
